quickjson/__init__.py
quickjson/quickjson.py
quickjson-0.0.2.dist-info/LICENSE
quickjson-0.0.2.dist-info/METADATA
quickjson-0.0.2.dist-info/WHEEL
quickjson-0.0.2.dist-info/top_level.txt
quickjson-0.0.2.dist-info/RECORD
